pytest_bq/__init__.py
pytest_bq/config.py
pytest_bq/plugin.py
pytest_bq/py.typed
pytest_bq/executor/__init__.py
pytest_bq/executor/process.py
pytest_bq/factories/__init__.py
pytest_bq/factories/client.py
pytest_bq/factories/proc.py
pytest_bq-0.0.4.dist-info/LICENSE
pytest_bq-0.0.4.dist-info/METADATA
pytest_bq-0.0.4.dist-info/WHEEL
pytest_bq-0.0.4.dist-info/entry_points.txt
pytest_bq-0.0.4.dist-info/top_level.txt
pytest_bq-0.0.4.dist-info/RECORD
